confng/__init__.py
confng/conf.py
confng/conf_test.py
confng_py-0.2.2.dist-info/METADATA
confng_py-0.2.2.dist-info/WHEEL
confng_py-0.2.2.dist-info/entry_points.txt
confng_py-0.2.2.dist-info/licenses/LICENSE
confng_py-0.2.2.dist-info/RECORD
