Metadata-Version: 2.4
Name: confng-py
Version: 0.2.2
Summary: A simple configuration management tool for python.
Project-URL: Homepage, https://github.com/SethWen/confng-py
Project-URL: Documentation, https://github.com/SethWen/confng-py#readme
Project-URL: Source, https://github.com/SethWen/confng-py
Project-URL: Tracker, https://github.com/SethWen/confng-py/issues
Author-email: Shawn Wen <coolrainerseth@gmail.com>
License-File: LICENSE
Classifier: License :: OSI Approved :: MIT License
Classifier: Operating System :: OS Independent
Classifier: Programming Language :: Python :: 3
Requires-Python: >=3.8
Requires-Dist: casefy>=1.1.0
